inkscape_mcp/__init__.py
inkscape_mcp/auto_flatten.py
inkscape_mcp/cli_server.py
inkscape_mcp/cli_server.py.bak
inkscape_mcp/combined.py
inkscape_mcp/config.py
inkscape_mcp/dom_server.py
iflow_mcp_grumpydevorg_inkscape_mcp-0.1.3.dist-info/METADATA
iflow_mcp_grumpydevorg_inkscape_mcp-0.1.3.dist-info/WHEEL
iflow_mcp_grumpydevorg_inkscape_mcp-0.1.3.dist-info/entry_points.txt
iflow_mcp_grumpydevorg_inkscape_mcp-0.1.3.dist-info/licenses/LICENSE
iflow_mcp_grumpydevorg_inkscape_mcp-0.1.3.dist-info/RECORD
