Metadata-Version: 2.4
Name: iflow-mcp_grumpydevorg_inkscape-mcp
Version: 0.1.3
Summary: MCP server for Inkscape CLI and DOM operations
Project-URL: Homepage, https://github.com/yourusername/inkscape-mcp
Project-URL: Repository, https://github.com/yourusername/inkscape-mcp
Project-URL: Issues, https://github.com/yourusername/inkscape-mcp/issues
Author-email: Your Name <your.email@example.com>
License: MIT License
License-File: LICENSE
Classifier: Development Status :: 4 - Beta
Classifier: Intended Audience :: Developers
Classifier: License :: OSI Approved :: MIT License
Classifier: Programming Language :: Python :: 3
Classifier: Programming Language :: Python :: 3.10
Classifier: Programming Language :: Python :: 3.11
Classifier: Programming Language :: Python :: 3.12
Requires-Python: >=3.10
Requires-Dist: anyio>=4.0.0
Requires-Dist: fastmcp>=2.0.0
Requires-Dist: filelock>=3.0.0
Requires-Dist: pydantic>=2.0.0
Requires-Dist: scour==0.38.2
Provides-Extra: dev
Requires-Dist: black>=23.0.0; extra == 'dev'
Requires-Dist: pytest-asyncio>=0.21.0; extra == 'dev'
Requires-Dist: pytest>=7.0.0; extra == 'dev'
Requires-Dist: ruff>=0.1.0; extra == 'dev'
Requires-Dist: ty>=0.0.1a19; extra == 'dev'
